fastembed/__init__.py
fastembed/common/__init__.py
fastembed/common/model_description.py
fastembed/common/model_management.py
fastembed/common/onnx_model.py
fastembed/common/preprocessor_utils.py
fastembed/common/types.py
fastembed/common/utils.py
fastembed/embedding.py
fastembed/image/__init__.py
fastembed/image/image_embedding.py
fastembed/image/image_embedding_base.py
fastembed/image/onnx_embedding.py
fastembed/image/onnx_image_model.py
fastembed/image/transform/functional.py
fastembed/image/transform/operators.py
fastembed/late_interaction/__init__.py
fastembed/late_interaction/colbert.py
fastembed/late_interaction/jina_colbert.py
fastembed/late_interaction/late_interaction_embedding_base.py
fastembed/late_interaction/late_interaction_text_embedding.py
fastembed/late_interaction/token_embeddings.py
fastembed/late_interaction_multimodal/__init__.py
fastembed/late_interaction_multimodal/colpali.py
fastembed/late_interaction_multimodal/late_interaction_multimodal_embedding.py
fastembed/late_interaction_multimodal/late_interaction_multimodal_embedding_base.py
fastembed/late_interaction_multimodal/onnx_multimodal_model.py
fastembed/parallel_processor.py
fastembed/postprocess/__init__.py
fastembed/postprocess/muvera.py
fastembed/py.typed
fastembed/rerank/cross_encoder/__init__.py
fastembed/rerank/cross_encoder/custom_text_cross_encoder.py
fastembed/rerank/cross_encoder/onnx_text_cross_encoder.py
fastembed/rerank/cross_encoder/onnx_text_model.py
fastembed/rerank/cross_encoder/text_cross_encoder.py
fastembed/rerank/cross_encoder/text_cross_encoder_base.py
fastembed/sparse/__init__.py
fastembed/sparse/bm25.py
fastembed/sparse/bm42.py
fastembed/sparse/minicoil.py
fastembed/sparse/sparse_embedding_base.py
fastembed/sparse/sparse_text_embedding.py
fastembed/sparse/splade_pp.py
fastembed/sparse/utils/minicoil_encoder.py
fastembed/sparse/utils/sparse_vectors_converter.py
fastembed/sparse/utils/tokenizer.py
fastembed/sparse/utils/vocab_resolver.py
fastembed/text/__init__.py
fastembed_qwen3-0.7.3.post3.dist-info/LICENSE
fastembed_qwen3-0.7.3.post3.dist-info/METADATA
fastembed_qwen3-0.7.3.post3.dist-info/NOTICE
fastembed_qwen3-0.7.3.post3.dist-info/WHEEL
fastembed_qwen3-0.7.3.post3.dist-info/RECORD
